<annotation>
	<folder>with_mask</folder>
	<filename>3-ply-tie-on-surgical-mask-yellow-500x500.jpg</filename>
	<path>C:\Users\zacca\OneDrive\Desktop\Year 4\Capstone\Code\CapstoneFaceMaskRemoval\train\with_mask\3-ply-tie-on-surgical-mask-yellow-500x500.jpg</path>
	<source>
		<database>Unknown</database>
	</source>
	<size>
		<width>500</width>
		<height>500</height>
		<depth>3</depth>
	</size>
	<segmented>0</segmented>
	<object>
		<name>mask</name>
		<pose>Unspecified</pose>
		<truncated>0</truncated>
		<difficult>0</difficult>
		<bndbox>
			<xmin>109</xmin>
			<ymin>244</ymin>
			<xmax>446</xmax>
			<ymax>493</ymax>
		</bndbox>
	</object>
</annotation>
